casbin/__init__.py
casbin/core_enforcer.py
casbin/distributed_enforcer.py
casbin/enforcer.py
casbin/frontend.py
casbin/internal_enforcer.py
casbin/management_enforcer.py
casbin/synced_enforcer.py
casbin/config/__init__.py
casbin/config/config.py
casbin/effect/__init__.py
casbin/effect/default_effectors.py
casbin/effect/effector.py
casbin/model/__init__.py
casbin/model/assertion.py
casbin/model/function.py
casbin/model/model.py
casbin/model/policy.py
casbin/model/policy_op.py
casbin/persist/__init__.py
casbin/persist/adapter.py
casbin/persist/adapter_filtered.py
casbin/persist/batch_adapter.py
casbin/persist/dispatcher.py
casbin/persist/watcher.py
casbin/persist/watcher_ex.py
casbin/persist/watcher_update.py
casbin/persist/adapters/__init__.py
casbin/persist/adapters/adapter_filtered.py
casbin/persist/adapters/file_adapter.py
casbin/persist/adapters/update_adapter.py
casbin/rbac/__init__.py
casbin/rbac/role_manager.py
casbin/rbac/default_role_manager/__init__.py
casbin/rbac/default_role_manager/role_manager.py
casbin/util/__init__.py
casbin/util/builtin_operators.py
casbin/util/expression.py
casbin/util/rwlock.py
casbin/util/util.py
tests/__init__.py
tests/test_distributed_api.py
tests/test_enforcer.py
tests/test_filter.py
tests/test_frontend.py
tests/test_management_api.py
tests/test_rbac_api.py
tests/benchmarks/__init__.py
tests/benchmarks/benchmark_management_api.py
tests/benchmarks/benchmark_model.py
tests/benchmarks/benchmark_role_manager.py
tests/config/__init__.py
tests/config/test_config.py
tests/model/__init__.py
tests/model/test_policy.py
tests/rbac/__init__.py
tests/rbac/test_role_manager.py
tests/util/__init__.py
tests/util/test_builtin_operators.py
tests/util/test_rwlock.py
tests/util/test_util.py
sa_casbin-1.1.0.dist-info/LICENSE
sa_casbin-1.1.0.dist-info/METADATA
sa_casbin-1.1.0.dist-info/WHEEL
sa_casbin-1.1.0.dist-info/top_level.txt
sa_casbin-1.1.0.dist-info/RECORD
