Metadata-Version: 2.1
Name: sa-casbin
Version: 1.1.0
Summary: 基于casbin改写符合态势感知业务逻辑的规则引擎
Home-page: UNKNOWN
Author: songtao
Author-email: 
License: UNKNOWN
Platform: UNKNOWN
Classifier: Programming Language :: Python :: 3
Classifier: License :: OSI Approved :: MIT License
Classifier: Operating System :: OS Independent
Requires-Python: >=3.6
License-File: LICENSE
